napari_bioimageio/VERSION
napari_bioimageio/__init__.py
napari_bioimageio/_bmm.py
napari_bioimageio/_utils.py
napari_bioimageio/bioimage-io-logo-white.png
napari_bioimageio/napari.yaml
napari_bioimageio-0.1.3.dist-info/LICENSE
napari_bioimageio-0.1.3.dist-info/METADATA
napari_bioimageio-0.1.3.dist-info/WHEEL
napari_bioimageio-0.1.3.dist-info/entry_points.txt
napari_bioimageio-0.1.3.dist-info/top_level.txt
napari_bioimageio-0.1.3.dist-info/RECORD
